urlpy2
urlpy2/urlpy2
