Metadata-Version: 2.1
Name: urlpy2
Version: 1.0.10
Summary: Simple URL parsing, canonicalization and equivalence.
Home-page: http://github.com/eon01/urlpy2
Author: Aymen El Amri based on code from nexB Inc
License: MIT
Platform: UNKNOWN
Classifier: License :: OSI Approved :: MIT License
Classifier: Development Status :: 3 - Alpha
Classifier: Environment :: Web Environment
Classifier: Intended Audience :: Developers
Classifier: Topic :: Internet :: WWW/HTTP
